accelon-0.0.1.dist-info/licenses/LICENSE
phlux/__init__.py
phlux/main.py
accelon-0.0.1.dist-info/METADATA
accelon-0.0.1.dist-info/WHEEL
accelon-0.0.1.dist-info/top_level.txt
accelon-0.0.1.dist-info/RECORD
