Metadata-Version: 2.4
Name: accelon
Version: 0.0.1
Summary: A simple 3d rendering engine for python.
Home-page: https://github.com/m-usman-k/accelon
Author: Muhammad Usman
Author-email: usmank.personal@outlook.com
License: MIT
Classifier: Programming Language :: Python :: 3
Classifier: License :: OSI Approved :: MIT License
Classifier: Operating System :: OS Independent
Requires-Python: >=3.8
License-File: LICENSE
Dynamic: author
Dynamic: author-email
Dynamic: description
Dynamic: description-content-type
Dynamic: home-page
Dynamic: license
Dynamic: license-file
Dynamic: requires-python
Dynamic: summary
